AiMetrix/__init__.py
AiMetrix/main.py
AiMetrix-0.0.1.dist-info/LICENCE
AiMetrix-0.0.1.dist-info/METADATA
AiMetrix-0.0.1.dist-info/WHEEL
AiMetrix-0.0.1.dist-info/top_level.txt
AiMetrix-0.0.1.dist-info/RECORD
