Metadata-Version: 2.1
Name: AiMetrix
Version: 0.0.1
Summary: A pakage that mesuares analytics of AI models
Home-page: https://github.com/gigDevelopment10/AiMetrix
Author: Zoya Jamadar
Author-email: zoya.jmd@gmail.com
Project-URL: Bug Tracker, https://github.com/gigDevelopment10/AiMetrix/issues
Classifier: Programming Language :: Python :: 3
Classifier: License :: OSI Approved :: MIT License
Classifier: Operating System :: OS Independent
Requires-Python: >=3.6
License-File: LICENCE
